cadscript/__init__.py
cadscript/assembly.py
cadscript/body.py
cadscript/construction_plane.py
cadscript/cqselectors.py
cadscript/export.py
cadscript/helpers.py
cadscript/interval.py
cadscript/patterns.py
cadscript/sketch.py
cadscript/typedefs.py
tests/__init__.py
tests/test_body_mirror.py
tests/test_body_move.py
tests/test_body_properties.py
tests/test_dxf.py
tests/test_examples.py
tests/test_helpers.py
tests/test_interval.py
tests/test_make_extrude.py
tests/test_make_text.py
tests/test_patterns.py
tests/test_sketch.py
tests/test_sketch_mirror.py
tests/test_sketch_move.py
cadscript-0.5.3.dist-info/LICENSE
cadscript-0.5.3.dist-info/METADATA
cadscript-0.5.3.dist-info/WHEEL
cadscript-0.5.3.dist-info/top_level.txt
cadscript-0.5.3.dist-info/RECORD
