Metadata-Version: 2.1
Name: cadscript
Version: 0.5.3
Summary: A Python module for creating 3D models with scripts.
Home-page: https://github.com/cadscriptHQ/cadscript
Author: Andreas Kahler
Author-email: mail@andreaskahler.com
License: Apache Public License 2.0
Classifier: Programming Language :: Python :: 3
Classifier: Development Status :: 3 - Alpha
Classifier: License :: OSI Approved :: Apache Software License
Requires-Python: >=3.8
License-File: LICENSE
Requires-Dist: numpy <2
Requires-Dist: cadquery >=2.4
